djangocms_misc/__init__.py
djangocms_misc/admin_style/__init__.py
djangocms_misc/admin_style/static/admin/djangocms_misc/css/admin_style.css
djangocms_misc/admin_style/static/admin/djangocms_misc/sass/admin_style.sass
djangocms_misc/admin_style/templates/admin/inc/extrastyle.html
djangocms_misc/alternate_toolbar/__init__.py
djangocms_misc/alternate_toolbar/cms_toolbars.py
djangocms_misc/apphook_templates/__init__.py
djangocms_misc/autopublisher/__init__.py
djangocms_misc/autopublisher/models.py
djangocms_misc/autopublisher/static/autopublisher/css/autopublisher.css
djangocms_misc/autopublisher/static/autopublisher/sass/autopublisher.sass
djangocms_misc/basic/__init__.py
djangocms_misc/basic/admin.py
djangocms_misc/basic/conf.py
djangocms_misc/basic/context_processors.py
djangocms_misc/basic/app_template/__init__.py
djangocms_misc/basic/app_template/admin.py
djangocms_misc/basic/app_template/cms_apps.py
djangocms_misc/basic/app_template/cms_menus.py
djangocms_misc/basic/app_template/managers.py
djangocms_misc/basic/app_template/models.py
djangocms_misc/basic/app_template/translation.py
djangocms_misc/basic/app_template/urls.py
djangocms_misc/basic/app_template/views.py
djangocms_misc/basic/app_template/views_utils.py
djangocms_misc/basic/app_template/migrations/__init__.py
djangocms_misc/basic/app_template/templates/app/app_detail.html
djangocms_misc/basic/app_template/templates/app/app_list.html
djangocms_misc/basic/app_template/tests/__init__.py
djangocms_misc/basic/app_template/tests/tst_app_basic.py
djangocms_misc/basic/management/__init__.py
djangocms_misc/basic/management/commands/__init__.py
djangocms_misc/basic/management/commands/djangocms_misc_add_cms_group.py
djangocms_misc/basic/management/commands/djangocms_misc_add_groups.py
djangocms_misc/basic/management/commands/djangocms_misc_startapp.py
djangocms_misc/basic/middleware/__init__.py
djangocms_misc/basic/middleware/bot404.py
djangocms_misc/basic/middleware/password_protected.py
djangocms_misc-0.3.0.dist-info/licenses/LICENSE
djangocms_misc-0.3.0.dist-info/METADATA
djangocms_misc-0.3.0.dist-info/WHEEL
djangocms_misc-0.3.0.dist-info/top_level.txt
djangocms_misc-0.3.0.dist-info/RECORD
