Metadata-Version: 2.4
Name: djangocms-misc
Version: 0.3.0
Summary: djangocms misc
Home-page: https://github.com/bnzk/djangocms-misc
Author: Ben Stähli
Author-email: bnzk@bnzk.ch
License: MIT Licence
Platform: OS Independent
Classifier: Development Status :: 4 - Beta
Classifier: Framework :: Django
Classifier: Intended Audience :: Developers
Classifier: License :: OSI Approved :: BSD License
Classifier: Operating System :: OS Independent
Classifier: Programming Language :: Python
Classifier: Topic :: Internet :: WWW/HTTP
License-File: LICENSE
Requires-Dist: django>=1.8
Requires-Dist: django-appconf>=1.0
Dynamic: author
Dynamic: author-email
Dynamic: classifier
Dynamic: description
Dynamic: description-content-type
Dynamic: home-page
Dynamic: license
Dynamic: license-file
Dynamic: platform
Dynamic: requires-dist
Dynamic: summary
